README.md
setup.py
bin/dicomsort
dicomsort/__init__.py
dicomsort/config.py
dicomsort/dicomsorter.py
dicomsort/errors.py
dicomsort/utils.py
dicomsort.egg-info/PKG-INFO
dicomsort.egg-info/SOURCES.txt
dicomsort.egg-info/dependency_links.txt
dicomsort.egg-info/not-zip-safe
dicomsort.egg-info/requires.txt
dicomsort.egg-info/top_level.txt
dicomsort/gui/__init__.py
dicomsort/gui/anonymizer.py
dicomsort/gui/core.py
dicomsort/gui/dialogs.py
dicomsort/gui/errors.py
dicomsort/gui/events.py
dicomsort/gui/help.py
dicomsort/gui/icons.py
dicomsort/gui/overrides.py
dicomsort/gui/preferences.py
dicomsort/gui/update.py
dicomsort/gui/widgets.py
tests/__init__.py
tests/conftest.py
tests/shared.py
tests/test_config.py
tests/test_dicomsorter.py
tests/test_errors.py
tests/test_utils.py