Metadata-Version: 2.1
Name: dicomsort
Version: 3.0.0
Summary: A DICOM Sorting Utility
Home-page: https://dicomsort.com
Author: Jonathan Suever
Author-email: suever@gmail.com
Maintainer: Jonathan Suever
Maintainer-email: suever@gmail.com
License: MIT
Download-URL: https://dicomsort.com/downloads.html
Keywords: dicom sorting images
Platform: UNKNOWN
Classifier: License :: OSI Approved :: MIT License
Classifier: Intended Audience :: Developers
Classifier: Intended Audience :: Healthcare Industry
Classifier: Intended Audience :: Science/Research
Classifier: Development Status :: 5 - Production/Stable
Classifier: Programming Language :: Python
Classifier: Programming Language :: Python :: 3.7
Classifier: Programming Language :: Python :: 3.8
Classifier: Programming Language :: Python :: 3.9
Classifier: Operating System :: OS Independent
Classifier: Topic :: Scientific/Engineering :: Medical Science Apps.
Classifier: Topic :: Scientific/Engineering :: Physics
Classifier: Topic :: Software Development :: Libraries
